kadoma/__init__.py
kadoma/__main__.py
kadoma/cli.py
kadoma/consts.py
kadoma/knobs.py
kadoma/mqtt.py
kadoma/transport.py
kadoma/unit.py
kadoma-0.0.3.dist-info/licenses/LICENSE
kadoma-0.0.3.dist-info/METADATA
kadoma-0.0.3.dist-info/WHEEL
kadoma-0.0.3.dist-info/entry_points.txt
kadoma-0.0.3.dist-info/top_level.txt
kadoma-0.0.3.dist-info/RECORD
