Metadata-Version: 2.4
Name: kadoma
Version: 0.0.3
Summary: Control Daikin BRC1H units over BLE (forked from pymadoka)
Author-email: "L. López" <luis@cuarentaydos.com>
Maintainer-email: "L. López" <luis@cuarentaydos.com>
License-Expression: MIT
Project-URL: Homepage, https://github.com/ldotlopez/kadoma
Project-URL: Repository, https://github.com/ldotlopez/kadoma
Project-URL: Issues, https://github.com/ldotlopez/kadoma/issues
Keywords: automation,ble,bluetooth,home-assistant,homeautomation,mqtt,thermostat
Requires-Python: >=3.13
License-File: LICENSE
Requires-Dist: bleak>=0.22.3
Dynamic: license-file
